pycountscjb/__init__.py
pycountscjb/plotting.py
pycountscjb/pycountscjb.py
pycountscjb-0.1.0.dist-info/LICENSE
pycountscjb-0.1.0.dist-info/METADATA
pycountscjb-0.1.0.dist-info/WHEEL
pycountscjb-0.1.0.dist-info/RECORD
